ddk/__init__.py
ddk/api/__init__.py
ddk/api/base.py
ddk/api/rest/DdkGoodsDetail.py
ddk/api/rest/DdkGoodsPidGenerate.py
ddk/api/rest/DdkGoodsPidQuery.py
ddk/api/rest/DdkGoodsPromotionUrlGenerate.py
ddk/api/rest/DdkGoodsSearch.py
ddk/api/rest/DdkGoodsZsUnitUrlGen.py
ddk/api/rest/DdkLotteryUrlGen.py
ddk/api/rest/DdkMallGoodsListGet.py
ddk/api/rest/DdkMallUrlGen.py
ddk/api/rest/DdkMerchantListGet.py
ddk/api/rest/DdkOrderDetailGet.py
ddk/api/rest/DdkOrderListIncrementGet.py
ddk/api/rest/DdkRpPromUrlGenerate.py
ddk/api/rest/DdkThemeGoodsSearch.py
ddk/api/rest/DdkThemeListGet.py
ddk/api/rest/DdkThemePromUrlGenerate.py
ddk/api/rest/DdkWeappQrcodeUrlGen.py
ddk/api/rest/GoodsCatsGet.py
ddk/api/rest/__init__.py
ddk-19.1.14.18.dist-info/DESCRIPTION.rst
ddk-19.1.14.18.dist-info/METADATA
ddk-19.1.14.18.dist-info/RECORD
ddk-19.1.14.18.dist-info/WHEEL
ddk-19.1.14.18.dist-info/metadata.json
ddk-19.1.14.18.dist-info/top_level.txt
