Metadata-Version: 2.0
Name: ddk
Version: 19.1.14.18
Summary: 拼多多-多多客联盟 CPS 工具包
Home-page: UNKNOWN
Author: play4fun
Author-email: play4fun@foxmail.com
License: MIT
Platform: UNKNOWN
